debrify/__init__.py
debrify/main.py
debrify/clients/__init__.py
debrify/clients/real_debrid_client.py
debrify/config/__init__.py
debrify/config/config.yaml
debrify/data/__init__.py
debrify/services/__init__.py
debrify/services/torrent_csv_database.py
debrify/services/torrent_csv_downloader.py
debrify/services/torrent_csv_search.py
debrify/utils/__init__.py
debrify/utils/common_utils.py
debrify-0.0.2.dist-info/LICENSE
debrify-0.0.2.dist-info/METADATA
debrify-0.0.2.dist-info/WHEEL
debrify-0.0.2.dist-info/entry_points.txt
debrify-0.0.2.dist-info/top_level.txt
debrify-0.0.2.dist-info/RECORD
