Metadata-Version: 2.1
Name: debrify
Version: 0.0.2
Summary: A CLI tool to search and add magnet into your real-debrid account
Home-page: https://github.com/varunsalian/debrify
Author: Varun Salian
Author-email: varunbsalian@gmail.com
Classifier: Programming Language :: Python :: 3
Classifier: License :: OSI Approved :: MIT License
Classifier: Operating System :: OS Independent
Requires-Python: >=3.8
License-File: LICENSE
Requires-Dist: PyYAML==6.0.1
Requires-Dist: rd-api-py==0.4.0
Requires-Dist: Requests
Requires-Dist: rich==13.9.4
Requires-Dist: setuptools==75.1.0
Requires-Dist: tqdm==4.66.5
Requires-Dist: duckdb
